dmx/__init__.py
dmx/colour.py
dmx/constants.py
dmx/interface.py
dmx/light.py
dmx/universe.py
dmx/drivers/__init__.py
dmx/drivers/debug.py
dmx/drivers/dummy.py
PyDMX-0.1.0.dist-info/LICENSE
PyDMX-0.1.0.dist-info/METADATA
PyDMX-0.1.0.dist-info/WHEEL
PyDMX-0.1.0.dist-info/top_level.txt
PyDMX-0.1.0.dist-info/RECORD
