Metadata-Version: 2.1
Name: PyDMX
Version: 0.1.0
Summary: A Python module for sending DMX512 data.
Author-email: Jacob Allen <jacob@polyomino.xyz>
License: BSD 3-Clause License
Project-URL: Homepage, https://github.com/JMAlego/PyDMX
Project-URL: Bug Tracker, https://github.com/JMAlego/PyDMX/issues
Classifier: Programming Language :: Python :: 3
Classifier: License :: OSI Approved :: BSD License
Classifier: Operating System :: OS Independent
Requires-Python: >=3.7
License-File: LICENSE
